LICENSE
README.md
setup.py
myskutils/__init__.py
myskutils/ci.py
myskutils/measure.py
myskutils/metric.py
myskutils/metrics.py
myskutils/plot.py
myskutils/stats.py
myskutils.egg-info/PKG-INFO
myskutils.egg-info/SOURCES.txt
myskutils.egg-info/dependency_links.txt
myskutils.egg-info/requires.txt
myskutils.egg-info/top_level.txt