Metadata-Version: 2.1
Name: myskutils
Version: 0.2.0
Summary: Small Python utils for Scikit-Learn.
Home-page: https://github.com/jmgomezsoriano/myskutils
Author: José Manuel Gómez Soriano
Author-email: jmgomez.soriano@gmail.com
License: LGPL2
Classifier: Programming Language :: Python :: 3
Classifier: License :: OSI Approved :: MIT License
Classifier: Operating System :: OS Independent
Requires-Python: >=3.10
License-File: LICENSE
